ndb_audit/__init__.py
ndb_audit-1.1.10.dist-info/METADATA
ndb_audit-1.1.10.dist-info/RECORD
ndb_audit-1.1.10.dist-info/WHEEL
ndb_audit-1.1.10.dist-info/entry_points.txt
ndb_audit-1.1.10.dist-info/top_level.txt
