Metadata-Version: 2.1
Name: ndb-audit
Version: 1.1.10
Summary: Adds audit trail to any Google Datastore NDB entity
Home-page: https://github.com/GainCompliance/ndb-audit
Author: Jason Jones
Author-email: jason@gaincompliance.com
License: MIT
Keywords: google,appengine,datastore,NDB,audit
Platform: UNKNOWN
Classifier: Programming Language :: Python
Classifier: Programming Language :: Python :: 2
